{
  "persons": [
    {
      "id": 1,
      "name": "Mary Poppendieck",
      "number": "39-23-6423122"
    },
    {
      "name": "Jay Mayer",
      "number": "123",
      "id": 3
    },
    {
      "name": "Malik",
      "number": "32424324",
      "id": 5
    },
    {
      "name": "Emiel",
      "number": "7890",
      "id": 6
    },
    {
      "name": "Harmienke",
      "number": "123",
      "id": 7
    },
    {
      "name": "Remi",
      "number": "123",
      "id": 8
    },
    {
      "name": "qwerty",
      "number": "123",
      "id": 10
    },
    {
      "name": "Cason",
      "number": "123",
      "id": 11
    }
  ]
}